{
  "basics": {
    "name": "Nolan Puletasi",
    "label": "Student",
    "picture": "https://sole808.github.io/images/Screenshot_2016-06-06-10-37-47 (2).png",
    "email": "np7798@moval.edu",
    "phone": "580-340-3608",
    "website": "https://sole808.github.io",
    "summary": "I am studying for a B.A. in Information of Computer Science at Missouri Valley College. I expect to graduate in Spring, 2020.",
    "location": {
      "address": "500 E College St.",
      "postalCode": "65340",
      "city": "Marshall",
      "countryCode": "USA",
      "region": "Missouri"
    },
    "profiles": [
      {
        "network": "github",
        "username": "sole808",
        "url": "http://github.com/sole808"
      },
      {
        "network": "linkedin",
        "username": "Nolan Puletasi",
        "url": "http://linkedin.com/in/nolan-puletasi-556b97b2"
      },
      {
        "network": "instagram",
        "username": "nolan.puletasi",
        "url": "http://instagram.com/nolanpuletasi"
      },
      {
        "network": "facebook",
        "username": "nolan.puletasi",
        "url": "http://facebook.com/nolanpuletasi"
      }
    ]
  },
  "interests": [
    {
      "name": "internet of things",
      "keywords": [
        "Alexa Amazon",
        ""
      ]
    },
    {
      "name": "data mining",
      "keywords": [
      ]
    },
    {
      "name": "artificial intelligence",
      "keywords": [
      ]
    }
  ],
  "skills": [
    {
      "name": "Languages and Frameworks",
      "level": "",
      "keywords": [
        "JavaScript"
      ]
    },
    {
      "name": "Toolsets/OS",
      "level": "",
      "keywords": [
        "MacOS",
        "Ubuntu",
        "Git/GitHub",
        "g++",
        "TI LaunchPad"
      ]
    }
  ],
  "education": [
    {
      "institution": "University of Hawaii, Honolulu, HI",
      "area": "Computer Science (expected Spring, 2020)",
      "studyType": "B.A.",
      "startDate": "2013-09-01",
      "endDate": "Present",
      "gpa": "",
      "courses": [
      ]
    }
  ],
  "work": [
    {
      "company": "",
      "position": "",
      "website": "",
      "startDate": "2015-08-01",
      "endDate": "Present",
      "summary": "",
      "highlights": [
        "",
        ""
      ]
    },
    {
      "company": "",
      "position": "",
      "website": "",
      "startDate": "",
      "endDate": "",
      "summary": "",
      "highlights": [
        "",
        ""
      ]
    }
  ],
  "volunteer": [
    {
      "organization": "",
      "website": "",
      "position": "",
      "startDate": "",
      "endDate": "",
      "summary": "",
      "highlights": [
        "",
        ""
      ]
    },
    {
      "organization": "",
      "website": "",
      "position": "",
      "startDate": "",
      "endDate": "",
      "summary": "",
      "highlights": [
        "",
        "",
        ""
      ]
    }
  ],
  "awards": [
    {
      "title": "",
      "date": "",
      "awarder": "",
      "summary": ""
    },
    {
      "title": "",
      "date": "",
      "awarder": "",
      "summary": ""
    }
  ],
  "references": [
    {
      "name": "Available upon request",
      "reference": ""
    }
  ]
}
